{"preview_id":"0d7526a5-0631-40b3-aecb-8229d4afb587","kb_id":"temp_kb","doc_id":"temp_doc","entity_count":58,"dictionary":{"오징어 게임":{"type":"EVENT","variants":["Squid Game","오징어 게임"],"chunk_ids":["doc_global"]},"황동혁":{"type":"PERSON","variants":["황동혁"],"chunk_ids":["doc_global"]},"넷플릭스":{"type":"ORGANIZATION","variants":["Netflix","넷플릭스"],"chunk_ids":["doc_global"]},"이정재":{"type":"PERSON","variants":["이정재"],"chunk_ids":["doc_global"]},"대한민국":{"type":"LOCATION","variants":["대한민국"],"chunk_ids":["doc_global"]},"456억 원":{"type":"OTHER","variants":["456억 원"],"chunk_ids":["doc_global"]},"오징어 놀이":{"type":"CONCEPT","variants":["오징어 (놀이)"],"chunk_ids":["doc_global"]},"프론트맨":{"type":"PERSON","variants":["프론트맨"],"chunk_ids":["doc_global"]},"성기훈":{"type":"PERSON","variants":["성기훈"],"chunk_ids":["doc_global"]},"조상우":{"type":"PERSON","variants":["조상우"],"chunk_ids":["doc_global"]},"강새벽":{"type":"PERSON","variants":["강새벽"],"chunk_ids":["doc_global"]},"황준호":{"type":"PERSON","variants":["황준호"],"chunk_ids":["doc_global"]},"오일남":{"type":"PERSON","variants":["오일남"],"chunk_ids":["doc_global"]},"장덕수":{"type":"PERSON","variants":["장덕수"],"chunk_ids":["doc_global"]},"알리 압둘":{"type":"PERSON","variants":["알리 압둘"],"chunk_ids":["doc_global"]},"한미녀":{"type":"PERSON","variants":["한미녀"],"chunk_ids":["doc_global"]},"Duke":{"type":"PERSON","variants":["Duke"],"chunk_ids":["doc_global"]},"황인호":{"type":"PERSON","variants":["황인호"],"chunk_ids":["doc_global"]},"박정배":{"type":"PERSON","variants":["박정배"],"chunk_ids":["doc_global"]},"이명기":{"type":"PERSON","variants":["이명기"],"chunk_ids":["doc_global"]},"강대호":{"type":"PERSON","variants":["강대호"],"chunk_ids":["doc_global"]},"조현주":{"type":"PERSON","variants":["조현주"],"chunk_ids":["doc_global"]},"박경석":{"type":"PERSON","variants":["박경석"],"chunk_ids":["doc_global"]},"박용식":{"type":"PERSON","variants":["박용식"],"chunk_ids":["doc_global"]},"김준희":{"type":"PERSON","variants":["김준희"],"chunk_ids":["doc_global"]},"장금자":{"type":"PERSON","variants":["장금자"],"chunk_ids":["doc_global"]},"강노을":{"type":"PERSON","variants":["강노을"],"chunk_ids":["doc_global"]},"선녀":{"type":"PERSON","variants":["선녀"],"chunk_ids":["doc_global"]},"박민수":{"type":"PERSON","variants":["박민수"],"chunk_ids":["doc_global"]},"최수봉":{"type":"PERSON","variants":["최수봉"],"chunk_ids":["doc_global"]},"남규":{"type":"PERSON","variants":["남규"],"chunk_ids":["doc_global"]},"세미":{"type":"PERSON","variants":["세미"],"chunk_ids":["doc_global"]},"김영미":{"type":"PERSON","variants":["김영미"],"chunk_ids":["doc_global"]},"최우석":{"type":"PERSON","variants":["최우석"],"chunk_ids":["doc_global"]},"오달수":{"type":"PERSON","variants":["오달수"],"chunk_ids":["doc_global"]},"싸이런픽쳐스":{"type":"ORGANIZATION","variants":["싸이런픽쳐스"],"chunk_ids":["doc_global"]},"정재일":{"type":"PERSON","variants":["정재일"],"chunk_ids":["doc_global"]},"프라임타임 에미상":{"type":"EVENT","variants":["프라임타임 에미상"],"chunk_ids":["doc_global"]},"골든 글로브상":{"type":"EVENT","variants":["골든 글로브상"],"chunk_ids":["doc_global"]},"2021년 9월 17일":{"type":"DATE","variants":["2021년 9월 17일"],"chunk_ids":["doc_global"]},"2024년 12월 26일":{"type":"DATE","variants":["2024년 12월 26일"],"chunk_ids":["doc_global"]},"2025년":{"type":"DATE","variants":["2025년"],"chunk_ids":["doc_global"]},"2026년":{"type":"DATE","variants":["2026년"],"chunk_ids":["doc_global"]},"The Guardian":{"type":"ORGANIZATION","variants":["The Guardian"],"chunk_ids":["doc_global"]},"Korean Drama":{"type":"CONCEPT","variants":["Korean Drama"],"chunk_ids":["doc_global"]},"HanCinema":{"type":"ORGANIZATION","variants":["HanCinema"],"chunk_ids":["doc_global"]},"ABS-CBN News":{"type":"ORGANIZATION","variants":["ABS-CBN News"],"chunk_ids":["doc_global"]},"YouTube":{"type":"ORGANIZATION","variants":["YouTube"],"chunk_ids":["doc_global"]},"Jennifer Maas":{"type":"PERSON","variants":["Jennifer Maas"],"chunk_ids":["doc_global"]},"Matt Minton":{"type":"PERSON","variants":["Matt Minton"],"chunk_ids":["doc_global"]},"Variety":{"type":"ORGANIZATION","variants":["Variety"],"chunk_ids":["doc_global"]},"2021년 10월 26일":{"type":"DATE","variants":["2021년 10월 26일"],"chunk_ids":["doc_global"]},"2021년 8월 11일":{"type":"DATE","variants":["2021년 8월 11일"],"chunk_ids":["doc_global"]},"2021년 8월 12일":{"type":"DATE","variants":["2021년 8월 12일"],"chunk_ids":["doc_global"]},"2021년 9월 15일":{"type":"DATE","variants":["2021년 9월 15일"],"chunk_ids":["doc_global"]},"2024년 12월 4일":{"type":"DATE","variants":["2024년 12월 4일"],"chunk_ids":["doc_global"]},"2024년 12월 5일":{"type":"DATE","variants":["2024년 12월 5일"],"chunk_ids":["doc_global"]},"2024년 12월 28일":{"type":"DATE","variants":["2024년 12월 28일"],"chunk_ids":["doc_global"]}},"message":"Entity Dictionary built successfully with 58 canonical entities."}